expr2gct.py
expr2gct-1.0.0.dist-info/LICENSE
expr2gct-1.0.0.dist-info/METADATA
expr2gct-1.0.0.dist-info/WHEEL
expr2gct-1.0.0.dist-info/entry_points.txt
expr2gct-1.0.0.dist-info/top_level.txt
expr2gct-1.0.0.dist-info/RECORD
