Metadata-Version: 2.1
Name: expr2gct
Version: 1.0.0
Summary: generate gct file (version 1.2, for GSEA or ssGSEA) from gene expression matrix file
Home-page: https://github.com/sxropensource/expr2gct
Author: sxropensource
Author-email: sxropensource@163.com
License: UNKNOWN
Keywords: GSEA ssGSEA GCT
Platform: UNKNOWN
Classifier: Topic :: Scientific/Engineering :: Bio-Informatics
Classifier: Development Status :: 5 - Production/Stable
Classifier: Intended Audience :: Developers
Classifier: Programming Language :: Python :: 3
Classifier: Programming Language :: Python :: 3.4
Classifier: Programming Language :: Python :: 3.5
Classifier: Programming Language :: Python :: 3.6
Classifier: Programming Language :: Python :: 3.7
